zgw_auth_backend/__init__.py
zgw_auth_backend/admin.py
zgw_auth_backend/apps.py
zgw_auth_backend/authentication.py
zgw_auth_backend/models.py
zgw_auth_backend/zgw.py
zgw_auth_backend/contrib/__init__.py
zgw_auth_backend/contrib/drf_spectacular.py
zgw_auth_backend/migrations/0001_initial.py
zgw_auth_backend/migrations/__init__.py
zgw_auth_backend-1.0.4.dist-info/LICENSE
zgw_auth_backend-1.0.4.dist-info/METADATA
zgw_auth_backend-1.0.4.dist-info/WHEEL
zgw_auth_backend-1.0.4.dist-info/top_level.txt
zgw_auth_backend-1.0.4.dist-info/RECORD
