Metadata-Version: 2.1
Name: zgw-auth-backend
Version: 1.0.4
Summary: A Django REST framework authentication class for the ZGW API authentication pattern.
Home-page: https://github.com/maykinmedia/zgw-auth-backend
Author: Maykin Media
Author-email: support@maykinmedia.nl
License: MIT
Keywords: zgw,vng,apis,drf
Platform: UNKNOWN
Classifier: Development Status :: 5 - Production/Stable
Classifier: Framework :: Django
Classifier: Framework :: Django :: 2.2
Classifier: Framework :: Django :: 3.0
Classifier: Framework :: Django :: 3.1
Classifier: Intended Audience :: Developers
Classifier: Operating System :: Unix
Classifier: Operating System :: MacOS
Classifier: Operating System :: Microsoft :: Windows
Classifier: Programming Language :: Python :: 3.7
Classifier: Programming Language :: Python :: 3.8
Classifier: Programming Language :: Python :: 3.9
Classifier: Topic :: Software Development :: Libraries :: Python Modules
Requires-Dist: django
Requires-Dist: djangorestframework
Requires-Dist: pyjwt
Provides-Extra: coverage
Requires-Dist: pytest-cov ; extra == 'coverage'
Provides-Extra: docs
Requires-Dist: sphinx ; extra == 'docs'
Requires-Dist: sphinx-rtd-theme ; extra == 'docs'
Provides-Extra: pep8
Requires-Dist: flake8 ; extra == 'pep8'
Provides-Extra: release
Requires-Dist: bump2version ; extra == 'release'
Requires-Dist: twine ; extra == 'release'
Provides-Extra: tests
Requires-Dist: pytest ; extra == 'tests'
Requires-Dist: pytest-django ; extra == 'tests'
Requires-Dist: tox ; extra == 'tests'
Requires-Dist: isort ; extra == 'tests'
Requires-Dist: gemma-zds-client (>=1.0.0) ; extra == 'tests'
Requires-Dist: black ; extra == 'tests'
